{"id":"Clotilde_(died_531)","label":"Clotilde (fille de Clovis)","abstract":"Clotilde la Jeune, aussi appelée Chrothieldis ou Chrothilda, est la fille de Clovis, issue de son union avec une princesse burgonde prénommée également Clotilde (seconde femme de Clovis).","birthDate":{"dateFormat":"yyyy","precise":false,"date":"0500-01-01T00:50:39.000Z"},"deathDate":{"dateFormat":"yyyy","precise":true,"date":"0531-01-01T00:50:39.000Z"},"activeYearsStartYear":"0526","activeYearsEndYear":"0531","child":[],"spouse":["Amalaric"]}
