{"id":"Yolande_of_Valois","label":"Yolande de France","house":"Maison de Valois","abstract":"Yolande de France ou Yolande de Valois, née à Tours le 23 septembre 1434, morte à Chambéry le 23 août 1478, fut duchesse de Savoie, puis régente du duché pour son fils Philibert. Elle est la fille de Charles VII, roi de France, et de Marie d'Anjou.","birthDate":{"dateFormat":"dd-mm-yyyy","precise":true,"date":"1434-09-23T00:00:00.000Z"},"deathDate":{"dateFormat":"dd-mm-yyyy","precise":true,"date":"1478-08-23T00:00:00.000Z"},"activeYearsStartYear":"1465","activeYearsEndYear":"1472","father":"Charles_VII_of_France","mother":"Marie_of_Anjou","child":["Louise_of_Savoy_(nun)","Charles_I,_Duke_of_Savoy","Philibert_I,_Duke_of_Savoy","Anne_of_Savoy"],"spouse":["Amadeus_IX,_Duke_of_Savoy"]}
